AstarCloud/__init__.py
AstarCloud/_exceptions.py
AstarCloud/_http.py
AstarCloud/_models.py
AstarCloud/_versions.py
AstarCloud/client.py
astarcloud-0.1.17.dist-info/METADATA
astarcloud-0.1.17.dist-info/WHEEL
astarcloud-0.1.17.dist-info/entry_points.txt
astarcloud-0.1.17.dist-info/RECORD
