Metadata-Version: 2.1
Name: astarcloud
Version: 0.1.17
Summary: Official Python SDK for the AstarCloud API
Author-Email: Erik <erik@astarconsulting.no>
License: MIT
Classifier: Programming Language :: Python :: 3
Classifier: License :: OSI Approved :: MIT License
Classifier: Operating System :: OS Independent
Project-URL: Documentation, https://docs.astarcloud.ai
Project-URL: Source, https://github.com/ASTAR-CLOUD/astarcloud-sdk
Requires-Python: >=3.9
Requires-Dist: httpx>=0.27.0
Requires-Dist: pydantic>=2.0
